conan_report/__init__.py
conan_report/__main__.py
conan_report/generate_conan_project_report.py
conan_report/git.py
conan_report/logger_manager.py
conan_report/run.py
conan_report/template_manager.py
conan_report/templates/soups_report_html.j2
lupin_conan_report-1.0.0.dist-info/LICENCE
lupin_conan_report-1.0.0.dist-info/METADATA
lupin_conan_report-1.0.0.dist-info/WHEEL
lupin_conan_report-1.0.0.dist-info/entry_points.txt
lupin_conan_report-1.0.0.dist-info/top_level.txt
lupin_conan_report-1.0.0.dist-info/RECORD
