Metadata-Version: 2.1
Name: lupin_conan_report
Version: 1.0.0
Summary: Tool used to generate a report about they SOUPS.
Author-email: LupinDental <contact@lupindental.com>
Maintainer-email: LupinDental <contact@lupindental.com>
Project-URL: Repository, https://gitlab.com/lupindental/arsene/devops/lupin_conan_report
Classifier: Programming Language :: Python :: 3.10
Classifier: Programming Language :: Python :: 3.11
Classifier: Programming Language :: Python :: 3.12
Classifier: Development Status :: 3 - Alpha
Requires-Python: >=3.10
License-File: LICENCE
Requires-Dist: jinja2 ==3.1.4
Requires-Dist: typer ==0.12.3
Provides-Extra: dev
Requires-Dist: coverage ; extra == 'dev'
Requires-Dist: pytest ; extra == 'dev'
